plume_learn/__init__.py
plume_learn/skeleton.py
plume_learn/ml_functions/__init__.py
plume_learn/ml_functions/build_model.py
plume_learn/ml_functions/hdf5_dataset.py
plume_learn/ml_functions/make_dataset.py
plume_learn/ml_functions/trainer.py
plume_learn/plume_analyzer/PlumeDataset.py
plume_learn/plume_analyzer/PlumeMetrics.py
plume_learn/plume_analyzer/Velocity.py
plume_learn/plume_analyzer/__init__.py
plume_learn/plume_analyzer/analyze_function.py
plume_learn/plume_utils/AutoAlign.py
plume_learn/plume_utils/HorizontalLineProfileAnalyzer.py
plume_learn/plume_utils/data_processing.py
plume_learn/plume_utils/manage_plume.py
plume_learn/plume_utils/viz.py
Plume_Learn-1.1.1.dist-info/LICENSE.txt
Plume_Learn-1.1.1.dist-info/METADATA
Plume_Learn-1.1.1.dist-info/WHEEL
Plume_Learn-1.1.1.dist-info/top_level.txt
Plume_Learn-1.1.1.dist-info/RECORD
