Metadata-Version: 2.2
Name: Plume-Learn
Version: 1.1.1
Summary: A Python package for visualizing and analyzing plume dynamics during thin-film growth, providing tools to process, visualize, and extract meaningful insights from in-situ plume images captured during Pulsed Laser Deposition (PLD) experiments.
Home-page: https://github.com/pyscaffold/pyscaffold/
Author: Yichen Guo
Author-email: yig319@lehigh.edu
License: MIT
Project-URL: Documentation, https://pyscaffold.org/
Platform: any
Classifier: Development Status :: 4 - Beta
Classifier: Programming Language :: Python
License-File: LICENSE.txt
Requires-Dist: importlib-metadata; python_version < "3.8"
Provides-Extra: testing
Requires-Dist: setuptools; extra == "testing"
Requires-Dist: pytest; extra == "testing"
Requires-Dist: pytest-cov; extra == "testing"
